yarllib/__init__.py
yarllib/callbacks.py
yarllib/core.py
yarllib/experiment_utils.py
yarllib/helpers/__init__.py
yarllib/helpers/base.py
yarllib/helpers/encoding.py
yarllib/helpers/history.py
yarllib/helpers/plots.py
yarllib/marl.py
yarllib/models/__init__.py
yarllib/models/tabular.py
yarllib/policies.py
yarllib/types.py
yarllib-0.2.0.dist-info/LICENSE
yarllib-0.2.0.dist-info/WHEEL
yarllib-0.2.0.dist-info/METADATA
yarllib-0.2.0.dist-info/RECORD
