Metadata-Version: 2.1
Name: yarllib
Version: 0.2.0
Summary: Yet Another Reinforcement Learning Library
Home-page: https://marcofavorito.github.io/yarllib
License: LGPL-3.0-or-later
Keywords: reinforcement learning,framework,openai gym
Author: MarcoFavorito
Author-email: marco.favorito@gmail.com
Requires-Python: >=3.7,<4.0
Classifier: Development Status :: 2 - Pre-Alpha
Classifier: Intended Audience :: Developers
Classifier: License :: OSI Approved :: GNU Lesser General Public License v3 or later (LGPLv3+)
Classifier: Natural Language :: English
Classifier: Programming Language :: Python :: 3
Classifier: Programming Language :: Python :: 3.7
Classifier: Programming Language :: Python :: 3.8
Requires-Dist: gym (>=0.17.2,<0.18.0)
Requires-Dist: matplotlib (>=3.3.2,<4.0.0)
Requires-Dist: numpy (>=1.19.2,<2.0.0)
Requires-Dist: pandas (>=1.1.2,<2.0.0)
Requires-Dist: scipy (>=1.5.2,<2.0.0)
Requires-Dist: seaborn (>=0.11.0,<0.12.0)
Project-URL: Bug Tracker, https://github.com/marcofavorito/yarllib/issues
Project-URL: Documentation, https://marcofavorito.github.io/yarllib
Project-URL: Pull Requests, https://github.com/marcofavorito/yarllib/pulls
Project-URL: Repository, https://github.com/marcofavorito/yarllib.git
